Pyfuso/__init__.py
Pyfuso/pyfuso.py
Pyfuso-0.0.10.dist-info/LICENSE
Pyfuso-0.0.10.dist-info/METADATA
Pyfuso-0.0.10.dist-info/WHEEL
Pyfuso-0.0.10.dist-info/top_level.txt
Pyfuso-0.0.10.dist-info/RECORD
